log_stacker/__init__.py
log_stacker/log_stacker.py
LogStacker-0.0.1.dist-info/LICENSE
LogStacker-0.0.1.dist-info/METADATA
LogStacker-0.0.1.dist-info/WHEEL
LogStacker-0.0.1.dist-info/top_level.txt
LogStacker-0.0.1.dist-info/RECORD
