Metadata-Version: 2.1
Name: LogStacker
Version: 0.0.1
Summary: A colorful and less settings logger, based on built-in package `logging`.
Home-page: https://github.com/Ron-Chang/Log Stacker
Author: Ron Chang
Author-email: ron.hsien.chang@gmail.com
License: MIT
Platform: UNKNOWN
Requires-Python: >=3.6
